qtmui/__init__.py
qtmui/configs.cp313-win_amd64.pyd
qtmui/configs.pyi
qtmui/errors.cp313-win_amd64.pyd
qtmui/errors.pyi
qtmui/logging.cp313-win_amd64.pyd
qtmui/logging.pyi
qtmui/mesage_handle.cp313-win_amd64.pyd
qtmui/mesage_handle.pyi
qtmui/qss_name.cp313-win_amd64.pyd
qtmui/qss_name.pyi
qtmui/common/__init__.py
qtmui/common/_config.cp313-win_amd64.pyd
qtmui/common/_config.pyi
qtmui/common/animation.cp313-win_amd64.pyd
qtmui/common/animation.pyi
qtmui/common/app_grips.cp313-win_amd64.pyd
qtmui/common/app_grips.pyi
qtmui/common/auto_wrap.cp313-win_amd64.pyd
qtmui/common/auto_wrap.pyi
qtmui/common/color.cp313-win_amd64.pyd
qtmui/common/color.pyi
qtmui/common/config.cp313-win_amd64.pyd
qtmui/common/config.pyi
qtmui/common/exception_handler.cp313-win_amd64.pyd
qtmui/common/exception_handler.pyi
qtmui/common/font.cp313-win_amd64.pyd
qtmui/common/font.pyi
qtmui/common/functions.cp313-win_amd64.pyd
qtmui/common/functions.pyi
qtmui/common/icon.cp313-win_amd64.pyd
qtmui/common/icon.pyi
qtmui/common/iconify.cp313-win_amd64.pyd
qtmui/common/iconify.pyi
qtmui/common/image_utils.cp313-win_amd64.pyd
qtmui/common/image_utils.pyi
qtmui/common/json_settings.cp313-win_amd64.pyd
qtmui/common/json_settings.pyi
qtmui/common/json_themes.cp313-win_amd64.pyd
qtmui/common/json_themes.pyi
qtmui/common/overload.cp313-win_amd64.pyd
qtmui/common/overload.pyi
qtmui/common/router.cp313-win_amd64.pyd
qtmui/common/router.pyi
qtmui/common/screen.cp313-win_amd64.pyd
qtmui/common/screen.pyi
qtmui/common/smooth_scroll.cp313-win_amd64.pyd
qtmui/common/smooth_scroll.pyi
qtmui/common/style_sheet.cp313-win_amd64.pyd
qtmui/common/style_sheet.pyi
qtmui/common/translator.cp313-win_amd64.pyd
qtmui/common/translator.pyi
qtmui/common/ui_functions.cp313-win_amd64.pyd
qtmui/common/ui_functions.pyi
qtmui/hooks/__init__.py
qtmui/hooks/_effect_context.cp313-win_amd64.pyd
qtmui/hooks/_effect_context.pyi
qtmui/hooks/_effect_runner.cp313-win_amd64.pyd
qtmui/hooks/_effect_runner.pyi
qtmui-0.0.47.dist-info/METADATA
qtmui-0.0.47.dist-info/WHEEL
qtmui-0.0.47.dist-info/licenses/LICENSE
qtmui-0.0.47.dist-info/RECORD
