Metadata-Version: 2.4
Name: qtmui
Version: 0.0.47
Summary: Python Desktop Application Development
Project-URL: Documentation, https://pyapp-kit.github.io/qtmui/
Project-URL: Source, https://github.com/pyapp-kit/qtmui
Project-URL: Tracker, https://github.com/pyapp-kit/qtmui/issues
Project-URL: Changelog, https://github.com/pyapp-kit/qtmui/blob/main/CHANGELOG.md
Author: SangPC
License: BSD 3-Clause License
License-File: LICENSE
Keywords: gui,pyqt,pyside,qt,qt components,qt flat ui,qt material ui,qt mui,qt range slider,qt widgets,qtmui
Classifier: Development Status :: 4 - Beta
Classifier: Environment :: X11 Applications :: Qt
Classifier: Intended Audience :: Developers
Classifier: License :: OSI Approved :: BSD License
Classifier: Operating System :: OS Independent
Classifier: Programming Language :: Python :: 3
Classifier: Programming Language :: Python :: 3 :: Only
Classifier: Programming Language :: Python :: 3.9
Classifier: Programming Language :: Python :: 3.10
Classifier: Programming Language :: Python :: 3.11
Classifier: Programming Language :: Python :: 3.12
Classifier: Programming Language :: Python :: 3.13
Classifier: Topic :: Desktop Environment
Classifier: Topic :: Software Development :: User Interfaces
Classifier: Topic :: Software Development :: Widget Sets
Requires-Python: >=3.9
Requires-Dist: markdown>=3.9
Requires-Dist: pyconify>=0.2.1
Requires-Dist: pygments>=2.4.0
Requires-Dist: pyside6>=6.9.2
Requires-Dist: pywin32>=308
Requires-Dist: qtpy>=2.4.0
Requires-Dist: typing-extensions>=4.12.0; python_version >= '3.13'
Requires-Dist: typing-extensions>=4.5.0
Provides-Extra: cmap
Requires-Dist: cmap>=0.2; extra == 'cmap'
Provides-Extra: font-fa5
Requires-Dist: fonticon-fontawesome5>=5.15.4; extra == 'font-fa5'
Provides-Extra: font-fa6
Requires-Dist: fonticon-fontawesome6>=6.4.0; extra == 'font-fa6'
Provides-Extra: font-mi6
Requires-Dist: fonticon-materialdesignicons6>=6.9.96; extra == 'font-mi6'
Provides-Extra: font-mi7
Requires-Dist: fonticon-materialdesignicons7>=7.2.96; extra == 'font-mi7'
Provides-Extra: iconify
Requires-Dist: pyconify>=0.1.4; extra == 'iconify'
Provides-Extra: pyqt5
Requires-Dist: pyqt5-qt5==5.15.2; (sys_platform == 'win32') and extra == 'pyqt5'
Requires-Dist: pyqt5-qt5>=5.15.16; (sys_platform != 'win32') and extra == 'pyqt5'
Requires-Dist: pyqt5>=5.15.10; extra == 'pyqt5'
Provides-Extra: pyqt6
Requires-Dist: pyqt6!=6.6,>=6.4.0; extra == 'pyqt6'
Requires-Dist: pyqt6!=6.6,>=6.7.0; (python_version >= '3.12') and extra == 'pyqt6'
Provides-Extra: pyside2
Requires-Dist: numpy<2,>=1.19; (python_version < '3.11') and extra == 'pyside2'
Requires-Dist: numpy<2,>=1.26; (python_version >= '3.11' and python_version < '3.13') and extra == 'pyside2'
Requires-Dist: pyside2>=5.15; extra == 'pyside2'
Provides-Extra: pyside6
Requires-Dist: pyside6!=6.5.0,!=6.5.1,!=6.6.2,>=6.4.0; extra == 'pyside6'
Requires-Dist: pyside6>=6.7.0; (python_version >= '3.12') and extra == 'pyside6'
Provides-Extra: quantity
Requires-Dist: pint>=0.21; extra == 'quantity'
